setup.py
rox_distributions/Binomialdistribution.py
rox_distributions/Gaussiandistribution.py
rox_distributions/Generaldistribution.py
rox_distributions/__init__.py
rox_distributions.egg-info/PKG-INFO
rox_distributions.egg-info/SOURCES.txt
rox_distributions.egg-info/dependency_links.txt
rox_distributions.egg-info/not-zip-safe
rox_distributions.egg-info/top_level.txt